necme/__about__.py
necme/__init__.py
necme/__main__.py
necme/protocol.py
necme/types.py
necme-0.1.0.dist-info/METADATA
necme-0.1.0.dist-info/WHEEL
necme-0.1.0.dist-info/RECORD
