Metadata-Version: 2.1
Name: necme
Version: 0.1.0
Summary: Management protocol for NE M and ME series video displays
Project-URL: Documentation, https://github.com/apparentlymart/python-necme#readme
Project-URL: Issues, https://github.com/apparentlymart/python-necme/issues
Project-URL: Source, https://github.com/apparentlymart/python-necme
Author-email: Martin Atkins <mart@degeneration.co.uk>
License-Expression: MIT
Classifier: Development Status :: 4 - Beta
Classifier: Programming Language :: Python
Classifier: Programming Language :: Python :: 3.10
Classifier: Programming Language :: Python :: 3.11
Classifier: Programming Language :: Python :: 3.12
Classifier: Programming Language :: Python :: Implementation :: CPython
Classifier: Programming Language :: Python :: Implementation :: PyPy
Requires-Python: >=3.10
